auth.py
fbs.py
main.py
hkust_fbs_automation-0.5.0.dist-info/entry_points.txt
hkust_fbs_automation-0.5.0.dist-info/METADATA
hkust_fbs_automation-0.5.0.dist-info/WHEEL
hkust_fbs_automation-0.5.0.dist-info/RECORD
