Metadata-Version: 2.1
Name: hkust-fbs-automation
Version: 0.5.0
Summary: Auto book facilities through the HKUST FBS.
Author: Poet
Author-email: the_poet@ust.hk
Requires-Python: >=3.10,<4.0
Classifier: Programming Language :: Python :: 3
Classifier: Programming Language :: Python :: 3.10
Classifier: Programming Language :: Python :: 3.11
Requires-Dist: requests (>=2.31,<3.0)
Requires-Dist: selenium (>=4.12,<5.0)
